wtftest/__init__.py
wtftest/wtftest.py
wtftest-1.0.0.dist-info/LICENSE
wtftest-1.0.0.dist-info/METADATA
wtftest-1.0.0.dist-info/WHEEL
wtftest-1.0.0.dist-info/top_level.txt
wtftest-1.0.0.dist-info/RECORD
