Metadata-Version: 2.1
Name: wtftest
Version: 1.0.0
Summary: just tell you a joke!
Home-page: https://www.python.org
Author: wangtf
Author-email: wangtf@qq.com
License: UNKNOWN
Platform: UNKNOWN
